{
  "fieldDescriptors": {

    "deleteAt": {
      "validOperators":["IS_NULL"],
      "hqlFieldName": "radiusSessionIp.deleteAt"
    },

    "createAt": {
      "validOperators":["GT_EQ", "LT_EQ", "LT", "GT"],
      "valueTypeName": "java.util.Date",
      "hqlFieldName": "radiusSessionIp.session.createAt",
      "sortable": true
    },

    "sessionId": {
      "validOperators":["EQ"],
      "valueTypeName":"java.lang.Long",
      "hqlFieldName": "radiusSessionIp.session.id"
    },

    "customerId": {
      "validOperators":["EQ"],
      "valueTypeName":"java.lang.Long",
      "hqlFieldName": "radiusSessionIp.session.customer.id"
    },

    "radiusUserId": {
      "validOperators":["EQ"],
      "valueTypeName":"java.lang.Long",
      "hqlFieldName": "radiusSessionIp.session.radiusUser.id"
    },

    "radiusClientId": {
      "validOperators":["EQ"],
      "valueTypeName":"java.lang.Long",
      "hqlFieldName": "radiusSessionIp.session.radiusClient.id"
    },

    "ipAddress": {
      "hqlFieldName": "radiusSessionIp.ipAddress",
      "validOperators":["EQ", "LIKE"],
      "valueTypeName":"java.lang.String"
    }

  },

  "defaultSort": "radiusSessionIp.session.createAt DESC"
}